{
    "$schema": "https://schema.management.azure.com/schemas/2015-01-01/deploymentTemplate.json#",
    "contentVersion": "1.0.0.0",
    "parameters": {
      "tenantstorType": {
        "type": "string",
        "defaultValue": "Standard_LRS",
        "allowedValues": [
          "Standard_LRS",
          "Standard_ZRS",
          "Standard_GRS",
          "Standard_RAGRS",
          "Premium_LRS"
        ]
      },
      "tenantvnetName": {
        "type": "string"
      },
      "tenantname": {
        "type": "string"
      },
        "VMName": {
            "type": "string",
            "minLength": 1
        },
        "VMAdminUserName": {
            "type": "string",
          "minLength": 1,
          "defaultValue": "localadmin"
        },
        "VMAdminPassword": {
            "type": "securestring"
        },
        "VMWindowsOSVersion": {
            "type": "string",
            "defaultValue": "2012-R2-Datacenter",
            "allowedValues": [
                "2008-R2-SP1",
                "2012-Datacenter",
                "2012-R2-Datacenter",
                "Windows-Server-Technical-Preview"
            ]
        },
        "workspaceId": {
            "type": "string",
            "metadata": {
                "description": "The Workspace ID is the Operations Management Suite Workspace ID found in the OMS Console under Settings and Connected Sources"
            }
        },
        "workspaceKey": {
            "type": "string",
            "metadata": {
                "description": "The Workspace Key is the Operations Management Suite Workspace Key found in the OMS Console under Settings and Connected Sources"
            }
        }
    },
  "variables": {
    "TenantVnetPrefix": "172.16.0.0/16",
    "TenantVnetSubnet1Name": "GatewaySubnet",
    "TenantVnetSubnet1Prefix": "172.16.0.0/29",
    "TenantVnetSubnet2Name": "TenantSubnet",
    "TenantVnetSubnet2Prefix": "172.16.1.0/24",
    "tenantstorName": "[concat('tenantstor', uniqueString(resourceGroup().id))]",
    "VMImagePublisher": "MicrosoftWindowsServer",
    "VMImageOffer": "WindowsServer",
    "VMOSDiskName": "VMOSDisk",
    "VMVmSize": "Standard_D1",
    "VMVnetID": "[resourceId('Microsoft.Network/virtualNetworks', parameters('tenantvnetName'))]",
    "VMSubnetRef": "[concat(variables('VMVnetID'), '/subnets/', variables('TenantVnetSubnet2Name'))]",
    "VMStorageAccountContainerName": "vhds",
    "VMNicName": "[concat(parameters('VMName'), 'NetworkInterface')]",
    "dc01pipName": "dc01pip"
  },
    "resources": [
      {
        "name": "[parameters('tenantvnetName')]",
        "type": "Microsoft.Network/virtualNetworks",
        "location": "[resourceGroup().location]",
        "apiVersion": "2015-06-15",
        "dependsOn": [ ],
        "tags": {
          "displayName": "[parameters('tenantvnetName')]",
          "tenantName" : "[parameters('tenantname')]"
        },
        "properties": {
          "addressSpace": {
            "addressPrefixes": [
              "[variables('TenantVnetPrefix')]"
            ]
          },
          "subnets": [
            {
              "name": "[variables('TenantVnetSubnet1Name')]",
              "properties": {
                "addressPrefix": "[variables('TenantVnetSubnet1Prefix')]"
              }
            },
            {
              "name": "[variables('TenantVnetSubnet2Name')]",
              "properties": {
                "addressPrefix": "[variables('TenantVnetSubnet2Prefix')]"
              }
            }
          ]
        }
      },
        {
            "name": "[variables('tenantstorName')]",
            "type": "Microsoft.Storage/storageAccounts",
            "location": "[resourceGroup().location]",
            "apiVersion": "2015-06-15",
            "dependsOn": [ ],
          "tags": {
            "displayName": "tenantstor",
            "tenantName": "[parameters('tenantname')]"
          },
            "properties": {
                "accountType": "[parameters('tenantstorType')]"
            }
        },
        {
            "name": "[variables('VMNicName')]",
            "type": "Microsoft.Network/networkInterfaces",
            "location": "[resourceGroup().location]",
            "apiVersion": "2015-06-15",
            "dependsOn": [
                "[concat('Microsoft.Network/virtualNetworks/', parameters('tenantvnetName'))]",
                "[concat('Microsoft.Network/publicIPAddresses/', variables('dc01pipName'))]"
            ],
          "tags": {
            "displayName": "VMNic",
            "tenantName": "[parameters('tenantname')]"
          },
            "properties": {
                "ipConfigurations": [
                    {
                        "name": "ipconfig1",
                        "properties": {
                            "privateIPAllocationMethod": "Dynamic",
                            "subnet": {
                                "id": "[variables('VMSubnetRef')]"
                            },
                            "publicIPAddress": {
                                "id": "[resourceId('Microsoft.Network/publicIPAddresses', variables('dc01pipName'))]"
                            }
                        }
                    }
                ]
            }
        },
        {
            "name": "[parameters('VMName')]",
            "type": "Microsoft.Compute/virtualMachines",
            "location": "[resourceGroup().location]",
            "apiVersion": "2015-06-15",
            "dependsOn": [
                "[concat('Microsoft.Storage/storageAccounts/', variables('tenantstorName'))]",
                "[concat('Microsoft.Network/networkInterfaces/', variables('VMNicName'))]"
            ],
          "tags": {
            "displayName": "VM",
            "tenantName": "[parameters('tenantname')]"
          },
            "properties": {
                "hardwareProfile": {
                    "vmSize": "[variables('VMVmSize')]"
                },
                "osProfile": {
                    "computerName": "[parameters('VMName')]",
                    "adminUsername": "[parameters('VMAdminUsername')]",
                    "adminPassword": "[parameters('VMAdminPassword')]"
                },
                "storageProfile": {
                    "imageReference": {
                        "publisher": "[variables('VMImagePublisher')]",
                        "offer": "[variables('VMImageOffer')]",
                        "sku": "[parameters('VMWindowsOSVersion')]",
                        "version": "latest"
                    },
                    "osDisk": {
                        "name": "VMOSDisk",
                        "vhd": {
                            "uri": "[concat('http://', variables('tenantstorName'), '.blob.core.windows.net/', variables('VMStorageAccountContainerName'), '/', variables('VMOSDiskName'), '.vhd')]"
                        },
                        "caching": "ReadWrite",
                        "createOption": "FromImage"
                    }
                },
                "networkProfile": {
                    "networkInterfaces": [
                        {
                            "id": "[resourceId('Microsoft.Network/networkInterfaces', variables('VMNicName'))]"
                        }
                    ]
                }
            },
            "resources": [
                {
                    "name": "Microsoft.EnterpriseCloud.Monitoring",
                    "type": "extensions",
                    "location": "[resourceGroup().location]",
                    "apiVersion": "2015-06-15",
                    "dependsOn": [
                        "[concat('Microsoft.Compute/virtualMachines/', parameters('VMName'))]"
                    ],
                  "tags": {
                    "displayName": "MOMAgent",
                    "tenantName": "[parameters('tenantname')]"
                  },
                    "properties": {
                        "publisher": "Microsoft.EnterpriseCloud.Monitoring",
                        "type": "MicrosoftMonitoringAgent",
                        "typeHandlerVersion": "1.0",
                        "autoUpgradeMinorVersion": true,
                        "settings": {
                            "workspaceId": "[parameters('workspaceId')]"
                        },
                        "protectedSettings": {
                            "workspaceKey": "[parameters('workspaceKey')]"
                        }
                    }
                }
            ]
        },
        {
            "name": "[variables('dc01pipName')]",
            "type": "Microsoft.Network/publicIPAddresses",
            "location": "[resourceGroup().location]",
            "apiVersion": "2015-06-15",
            "dependsOn": [ ],
          "tags": {
            "displayName": "VMpip",
            "tenantName": "[parameters('tenantname')]"
          },
            "properties": {
                "publicIPAllocationMethod": "Dynamic"
            }
        }
    ],
    "outputs": {
    }
}
